[
  {
    "id": "F-4B2H1",
    "_kind": "found",
    "reportAs": "found",
    "category": "Electronics",
    "type": "Earphones",
    "brand": "Sony",
    "model": "WF-1000XM3",
    "color": "White",
    "accessories": "Charging case",
    "condition": "Used",
    "serial": "SN-EAR-7733",
    "image": "sony_earbuds.jpg",
    "locationFound": "Cafeteria (Table near entrance)",
    "dateFound": "2025-11-03",
    "foundBy": "Kyle Mendoza",
    "contact": "09281234567",
    "storedAt": "Security Office - Ground Floor",
    "status": "Unclaimed",
    "postedAt": "2025-11-03",
    "lastUpdated": "2025-11-03"
  },
  {
    "id": "F-5K8P2",
    "_kind": "found",
    "reportAs": "found",
    "category": "Electronics",
    "type": "Smartwatch",
    "brand": "Samsung",
    "model": "Galaxy Watch 4",
    "color": "Silver",
    "accessories": "Original strap",
    "condition": "Slightly Used",
    "serial": "SW-4578-SG",
    "image": "samsung_watch.jpg",
    "locationFound": "Gymnasium - Locker Area",
    "dateFound": "2025-10-29",
    "foundBy": "Rhea Cruz",
    "contact": "09184561234",
    "storedAt": "Lost & Found - Admin Office",
    "status": "Unclaimed",
    "postedAt": "2025-10-30",
    "lastUpdated": "2025-10-30"
  },
  {
    "id": "F-6M4Q7",
    "_kind": "found",
    "reportAs": "found",
    "category": "Personal Items",
    "type": "Umbrella",
    "brand": "Fulton",
    "model": "Compact",
    "color": "Black",
    "accessories": "Wrist strap",
    "condition": "Good",
    "serial": "UM-0042",
    "image": "umbrella_black.jpg",
    "locationFound": "Gate 2 (near bus stop)",
    "dateFound": "2025-11-04",
    "foundBy": "Security - Guard #12",
    "contact": "020-555-0199",
    "storedAt": "Security Office - Gate 2",
    "status": "Unclaimed",
    "postedAt": "2025-11-04",
    "lastUpdated": "2025-11-04"
  }
]